vws_auth_tools/__init__.py
vws_auth_tools/py.typed
vws_auth_tools-2024.7.12.dist-info/LICENSE
vws_auth_tools-2024.7.12.dist-info/METADATA
vws_auth_tools-2024.7.12.dist-info/WHEEL
vws_auth_tools-2024.7.12.dist-info/top_level.txt
vws_auth_tools-2024.7.12.dist-info/RECORD
