Metadata-Version: 2.1
Name: vws-auth-tools
Version: 2024.7.12
Summary: Authentication and authorization tools for interacting with the Vuforia Web Services (VWS) API.
Author-email: Adam Dangoor <adamdangoor@gmail.com>
License: MIT License
Project-URL: Source, https://github.com/VWS-Python/vws-auth-tools
Keywords: vuforia,vws
Classifier: Development Status :: 5 - Production/Stable
Classifier: Environment :: Web Environment
Classifier: License :: OSI Approved :: MIT License
Classifier: Operating System :: POSIX
Classifier: Programming Language :: Python :: 3 :: Only
Classifier: Programming Language :: Python :: 3.10
Classifier: Programming Language :: Python :: 3.11
Classifier: Programming Language :: Python :: 3.12
Requires-Python: >=3.10
License-File: LICENSE
Provides-Extra: dev
Requires-Dist: actionlint-py ==1.7.1.15 ; extra == 'dev'
Requires-Dist: check-manifest ==0.49 ; extra == 'dev'
Requires-Dist: deptry ==0.16.2 ; extra == 'dev'
Requires-Dist: doc8 ==1.1.1 ; extra == 'dev'
Requires-Dist: freezegun ==1.5.1 ; extra == 'dev'
Requires-Dist: furo ==2024.5.6 ; extra == 'dev'
Requires-Dist: interrogate ==1.7.0 ; extra == 'dev'
Requires-Dist: mypy ==1.10.1 ; extra == 'dev'
Requires-Dist: pre-commit ==3.7.1 ; extra == 'dev'
Requires-Dist: pylint ==3.2.5 ; extra == 'dev'
Requires-Dist: pyproject-fmt ==2.1.4 ; extra == 'dev'
Requires-Dist: pyright ==1.1.371 ; extra == 'dev'
Requires-Dist: pyroma ==4.2 ; extra == 'dev'
Requires-Dist: pytest ==8.2.2 ; extra == 'dev'
Requires-Dist: pytest-cov ==5.0.0 ; extra == 'dev'
Requires-Dist: ruff ==0.5.1 ; extra == 'dev'
Requires-Dist: sphinx ==7.3.7 ; extra == 'dev'
Requires-Dist: sphinx-prompt ==1.8 ; extra == 'dev'
Requires-Dist: sphinx-substitution-extensions ==2024.2.25 ; extra == 'dev'
Requires-Dist: sphinxcontrib-spelling ==8 ; extra == 'dev'
Requires-Dist: sybil ==6.1.1 ; extra == 'dev'
Requires-Dist: vulture ==2.11 ; extra == 'dev'
Requires-Dist: vws-python-mock ==2024.7.2.1 ; extra == 'dev'
